pyslz/__init__.py
pyslz/pyslz.py
pyslz-5.0.3.dist-info/METADATA
pyslz-5.0.3.dist-info/WHEEL
pyslz-5.0.3.dist-info/top_level.txt
pyslz-5.0.3.dist-info/RECORD
