Metadata-Version: 2.1
Name: pyslz
Version: 5.0.3
Summary: Usefull functions
Home-page: UNKNOWN
Author: Eduardo Maia
Author-email: <maia@pessoalize.com>
License: UNKNOWN
Keywords: pyslz
Platform: UNKNOWN
Classifier: Development Status :: 1 - Planning
Classifier: Intended Audience :: Developers
Classifier: Programming Language :: Python :: 3
Classifier: Operating System :: Unix
Classifier: Operating System :: MacOS :: MacOS X
Classifier: Operating System :: Microsoft :: Windows
